geomcp/__init__.py
geomcp/geo_downloader.py
geomcp/geo_profiles.py
geomcp/main.py
geomcp/mcp_http_server.py
geomcp/mcp_server.py
geo_mcp-0.1.0.dist-info/METADATA
geo_mcp-0.1.0.dist-info/WHEEL
geo_mcp-0.1.0.dist-info/entry_points.txt
geo_mcp-0.1.0.dist-info/licenses/LICENSE
geo_mcp-0.1.0.dist-info/RECORD
