Metadata-Version: 2.4
Name: geo-mcp
Version: 0.1.0
Summary: A Model Context Protocol (MCP) server for accessing GEO (Gene Expression Omnibus) data through NCBI E-Utils API
Project-URL: Homepage, https://github.com/MCPmed/geomcp
Project-URL: Repository, https://github.com/MCPmed/geomcp
Project-URL: Documentation, https://github.com/MCPmed/geomcp#readme
Project-URL: Bug Tracker, https://github.com/MCPmed/geomcp/issues
Author-email: MCPmed Contributors <matthias.flotho@ccb.uni-saarland.de>
License: MIT
License-File: LICENSE
Keywords: bioinformatics,e-utils,gene-expression,geo,mcp,ncbi
Classifier: Development Status :: 3 - Alpha
Classifier: Intended Audience :: Science/Research
Classifier: License :: OSI Approved :: MIT License
Classifier: Operating System :: OS Independent
Classifier: Programming Language :: Python :: 3
Classifier: Programming Language :: Python :: 3.10
Classifier: Programming Language :: Python :: 3.11
Classifier: Programming Language :: Python :: 3.12
Classifier: Topic :: Scientific/Engineering :: Bio-Informatics
Classifier: Topic :: Software Development :: Libraries :: Python Modules
Requires-Python: >=3.10
Requires-Dist: aiofiles>=23.0.0
Requires-Dist: aiohttp>=3.8.0
Requires-Dist: fastapi>=0.100.0
Requires-Dist: mcp[cli]>=1.9.4
Requires-Dist: requests>=2.31.0
Requires-Dist: uvicorn>=0.20.0
Provides-Extra: dev
Requires-Dist: black>=23.0.0; extra == 'dev'
Requires-Dist: mypy>=1.0.0; extra == 'dev'
Requires-Dist: pytest-asyncio>=0.21.0; extra == 'dev'
Requires-Dist: pytest>=7.0.0; extra == 'dev'
Requires-Dist: ruff>=0.1.0; extra == 'dev'
Provides-Extra: test
Requires-Dist: pytest-asyncio>=0.21.0; extra == 'test'
Requires-Dist: pytest>=7.0.0; extra == 'test'
